Fyreside-0.0.4.data/scripts/fyreside_run
Fyreside-0.0.4.dist-info/DESCRIPTION.rst
Fyreside-0.0.4.dist-info/METADATA
Fyreside-0.0.4.dist-info/RECORD
Fyreside-0.0.4.dist-info/WHEEL
Fyreside-0.0.4.dist-info/metadata.json
Fyreside-0.0.4.dist-info/top_level.txt
fyreside/__init__.py
fyreside/cards.py
fyreside/cmds.py
fyreside/services.py
fyreside/subscriptions.py
fyreside/txt.py
